Workbook
Name k_Inputs_case: Inputs!$A$5
Name k_Inputs_case_idx: Inputs!$A$6
Name k_Inputs_g: Inputs!$A$22
Name k_Inputs_j24: Inputs!$A$9
Name k_Inputs_j26: Inputs!$A$8
Name k_Inputs_m0: Inputs!$A$18
Name k_Inputs_price: Inputs!$A$11
Name k_Inputs_roic: Inputs!$A$16
Name k_Inputs_s2c: Inputs!$A$15
Name k_Inputs_shares: Inputs!$A$12
Name k_Inputs_target_margin: Inputs!$A$21
Name k_Inputs_tax: Inputs!$A$14
Name k_Inputs_w27: Inputs!$A$19
Name k_Inputs_wacc: Inputs!$A$17
Name k_Model_df: Model!$A$21
Name k_Model_ebit: Model!$A$17
Name k_Model_fcf: Model!$A$20
Name k_Model_growth: Model!$A$13
Name k_Model_growth_base: Model!$A$11
Name k_Model_growth_bear: Model!$A$10
Name k_Model_growth_bull: Model!$A$12
Name k_Model_margin: Model!$A$16
Name k_Model_nopat: Model!$A$18
Name k_Model_pv: Model!$A$22
Name k_Model_reinv: Model!$A$19
Name k_Model_rev: Model!$A$14
Name k_Model_t: Model!$A$5
Name k_Model_t_end: Model!$A$7
Name k_Model_t_mid: Model!$A$8
Name k_Model_w: Model!$A$6
Name k_Valuation_ebit31: Valuation!$A$15
Name k_Valuation_eps31: Valuation!$A$16
Name k_Valuation_ev: Valuation!$A$10
Name k_Valuation_nopat_next: Valuation!$A$5
Name k_Valuation_pct_price: Valuation!$A$12
Name k_Valuation_per_share: Valuation!$A$11
Name k_Valuation_pv_fcf: Valuation!$A$9
Name k_Valuation_pv_tv: Valuation!$A$7
Name k_Valuation_tv: Valuation!$A$6
Name k_Valuation_tv_share: Valuation!$A$13
Name k_Valuation_vs_peak: Valuation!$A$17
Name MasterCheck: Checks!$D$9

Sheet Cover
A1: Jordan Brand scenario valuation (illustrative)
A2: Assumption-driven DCF of Jordan Brand; growth, margin and terminal growth are labelled ASSUMPTIONS, not forecasts. Mirror of scripts/jordan_valuation.py.
A4: Master check | B4: =IF(MasterCheck=1,"OK: all checks pass","ERROR: see Checks sheet") -> OK: all checks pass
A6: Colour key
A7: Blue text | B7: hard-coded input (change these)
A8: Black text | B8: formula
A9: Green text | B9: link from another sheet
A10: Yellow fill | B10: scenario switch
A12: Sheets
A13: Inputs | B13: Scenario switch, filing facts, market data and DCF conventions
A14: Model | B14: Revenue path, margin ramp, free cash flow and discounting by fiscal year
A15: Valuation | B15: DCF value, per-share value and terminal share for the active scenario
A16: Charts | B16: Value bridge for the active scenario and the per-share football field

Sheet Inputs
A1: Inputs
A3: Item | B3: Unit | C3: Live | D3: Bear | E3: Base | F3: Bull | G3: Source / note
A4: Scenario
A5: Active scenario | C5: Base | G5: Pick a case; every scenario row follows it
A6: Active scenario (index) | B6: # | C6: =MATCH($C$5,{"Bear","Base","Bull"},0) -> 2 | G6: derived from the switch above
A7: Filing facts ($m)
A8: Jordan revenue FY2026 | B8: $m | C8: 7034 | G8: FY2026 Form 10-K (filed 2026-07-15) p. 32
A9: Jordan revenue FY2024 (peak) | B9: $m | C9: 8701 | G9: FY2026 Form 10-K (filed 2026-07-15) p. 32
A10: Market data
A11: NKE share price | B11: $ | C11: 35.35 | G11: market data, data/valuation/peer_multiples.csv (Oct 13, 2026)
A12: NKE diluted shares (m) | B12: # | C12: 1487 | G12: Convention shared with the reverse DCF (research_notes/thesis_tests/consensus_and_valuation.md Section C)
A13: DCF conventions
A14: Tax rate | B14: % | C14: 0.225 | G14: Convention shared with the reverse DCF (research_notes/thesis_tests/consensus_and_valuation.md Section C)
A15: Sales to capital | B15: x | C15: 2.5 | G15: Convention shared with the reverse DCF (research_notes/thesis_tests/consensus_and_valuation.md Section C)
A16: Terminal ROIC | B16: % | C16: 0.2 | G16: Convention shared with the reverse DCF (research_notes/thesis_tests/consensus_and_valuation.md Section C)
A17: WACC | B17: % | C17: 0.1 | G17: Convention shared with the reverse DCF (research_notes/thesis_tests/consensus_and_valuation.md Section C)
A18: FY2027 starting EBIT margin | B18: % | C18: 0.057 | G18: FY2027 consolidated margin implied by consensus EPS; Convention shared with the reverse DCF (research_notes/thesis_tests/consensus_and_valuation.md Section C)
A19: FY2027 weight (valuation date 2026-10-12) | B19: yrs | C19: 0.63 | G19: Convention shared with the reverse DCF (research_notes/thesis_tests/consensus_and_valuation.md Section C)
A20: Scenario assumptions (ASSUMPTIONS)
A21: Steady-state EBIT margin, reached FY2031 | B21: % | C21: =CHOOSE($C$6,D21,E21,F21) -> 0.11 | D21: 0.08 | E21: 0.11 | F21: 0.14 | G21: ASSUMPTION; see research_notes/12_jordan_brand_thesis.md
A22: Terminal growth | B22: % | C22: =CHOOSE($C$6,D22,E22,F22) -> 0.025 | D22: 0.01 | E22: 0.025 | F22: 0.03 | G22: ASSUMPTION

Sheet Model
A1: Model
A3: Fiscal year | B3: Unit | C3: FY2027E | D3: FY2028E | E3: FY2029E | F3: FY2030E | G3: FY2031E
A4: Timing
A5: Period number | B5: # | C5: =1 -> 1 | D5: =C5+1 -> 2 | E5: =D5+1 -> 3 | F5: =E5+1 -> 4 | G5: =F5+1 -> 5
A6: Year weight (FY2027 pro-rated) | B6: yrs | C6: =Inputs!$C$19 -> 0.63 | D6: =1 -> 1 | E6: =1 -> 1 | F6: =1 -> 1 | G6: =1 -> 1
A7: Years from valuation date, period end | B7: yrs | C7: =C6 -> 0.63 | D7: =C7+D6 -> 1.63 | E7: =D7+E6 -> 2.63 | F7: =E7+F6 -> 3.63 | G7: =F7+G6 -> 4.63
A8: Discount timing, mid-period | B8: yrs | C8: =C7-C6/2 -> 0.315 | D8: =D7-D6/2 -> 1.13 | E8: =E7-E6/2 -> 2.13 | F8: =F7-F6/2 -> 3.13 | G8: =G7-G6/2 -> 4.13
A9: Revenue
A10: Revenue growth: Bear | B10: % | C10: -0.15 | D10: -0.08 | E10: 0 | F10: 0 | G10: 0 | H10: ASSUMPTION; FY2027 -15% from Q1 FY27 'mid-teens' decline (Nike transcript, Oct 1, 2026)
A11: Revenue growth: Base | B11: % | C11: -0.15 | D11: -0.03 | E11: 0.05 | F11: 0.05 | G11: 0.05 | H11: ASSUMPTION; FY2027 -15% from Q1 FY27 'mid-teens' decline (Nike transcript, Oct 1, 2026)
A12: Revenue growth: Bull | B12: % | C12: -0.15 | D12: 0.05 | E12: 0.12 | F12: 0.12 | G12: 0.1 | H12: ASSUMPTION; FY2027 -15% from Q1 FY27 'mid-teens' decline (Nike transcript, Oct 1, 2026)
A13: Revenue growth (live) | B13: % | C13: =CHOOSE(Inputs!$C$6,C10,C11,C12) -> -0.15 | D13: =CHOOSE(Inputs!$C$6,D10,D11,D12) -> -0.03 | E13: =CHOOSE(Inputs!$C$6,E10,E11,E12) -> 0.05 | F13: =CHOOSE(Inputs!$C$6,F10,F11,F12) -> 0.05 | G13: =CHOOSE(Inputs!$C$6,G10,G11,G12) -> 0.05
A14: Jordan revenue | B14: $m | C14: =Inputs!$C$8*(1+C13) -> 5978.9 | D14: =C14*(1+D13) -> 5799.533 | E14: =D14*(1+E13) -> 6089.5096 | F14: =E14*(1+F13) -> 6393.9851 | G14: =F14*(1+G13) -> 6713.6844
A15: Profit and cash flow
A16: EBIT margin (linear ramp to target) | B16: % | C16: =Inputs!$C$18+(Inputs!$C$21-Inputs!$C$18)*(C5-1)/(MAX($C$5:$G$5)-1) -> 0.057 | D16: =Inputs!$C$18+(Inputs!$C$21-Inputs!$C$18)*(D5-1)/(MAX($C$5:$G$5)-1) -> 0.07025 | E16: =Inputs!$C$18+(Inputs!$C$21-Inputs!$C$18)*(E5-1)/(MAX($C$5:$G$5)-1) -> 0.0835 | F16: =Inputs!$C$18+(Inputs!$C$21-Inputs!$C$18)*(F5-1)/(MAX($C$5:$G$5)-1) -> 0.09675 | G16: =Inputs!$C$18+(Inputs!$C$21-Inputs!$C$18)*(G5-1)/(MAX($C$5:$G$5)-1) -> 0.11
A17: EBIT | B17: $m | C17: =C14*C16 -> 340.7973 | D17: =D14*D16 -> 407.41719 | E17: =E14*E16 -> 508.47406 | F17: =F14*F16 -> 618.61806 | G17: =G14*G16 -> 738.50528
A18: NOPAT | B18: $m | C18: =C17*(1-Inputs!$C$14) -> 264.11791 | D18: =D17*(1-Inputs!$C$14) -> 315.74832 | E18: =E17*(1-Inputs!$C$14) -> 394.06739 | F18: =F17*(1-Inputs!$C$14) -> 479.429 | G18: =G17*(1-Inputs!$C$14) -> 572.34159
A19: Reinvestment (revenue growth / sales to capital, floored at 0) | B19: $m | C19: =MAX(C14-Inputs!$C$8,0)/Inputs!$C$15 -> 0 | D19: =MAX(D14-C14,0)/Inputs!$C$15 -> 0 | E19: =MAX(E14-D14,0)/Inputs!$C$15 -> 115.99066 | F19: =MAX(F14-E14,0)/Inputs!$C$15 -> 121.79019 | G19: =MAX(G14-F14,0)/Inputs!$C$15 -> 127.8797
A20: Free cash flow, period-weighted | B20: $m | C20: =(C18-C19)*C6 -> 166.39428 | D20: =(D18-D19)*D6 -> 315.74832 | E20: =(E18-E19)*E6 -> 278.07673 | F20: =(F18-F19)*F6 -> 357.6388 | G20: =(G18-G19)*G6 -> 444.46189
A21: Discount factor | B21: factor | C21: =1/(1+Inputs!$C$17)^C8 -> 0.9704235 | D21: =1/(1+Inputs!$C$17)^D8 -> 0.89789647 | E21: =1/(1+Inputs!$C$17)^E8 -> 0.81626952 | F21: =1/(1+Inputs!$C$17)^F8 -> 0.7420632 | G21: =1/(1+Inputs!$C$17)^G8 -> 0.67460291
A22: PV of free cash flow | B22: $m | C22: =C20*C21 -> 161.47292 | D22: =D20*D21 -> 283.50931 | E22: =E20*E21 -> 226.98556 | F22: =F20*F21 -> 265.3906 | G22: =G20*G21 -> 299.83529

Sheet Valuation
A1: Valuation
A3: Item | B3: Unit | C3: Live | D3: Source / note
A4: Terminal value
A5: NOPAT FY2032 (FY2031 x (1+g)) | B5: $m | C5: =Model!$G$14*Model!$G$16*(1-Inputs!$C$14)*(1+Inputs!$C$22) -> 586.65013
A6: Terminal value at FY2031 (value driver formula) | B6: $m | C6: =$C$5*(1-Inputs!$C$22/Inputs!$C$16)/(Inputs!$C$17-Inputs!$C$22) -> 6844.2516
A7: PV of terminal value | B7: $m | C7: =$C$6/(1+Inputs!$C$17)^Model!$G$7 -> 4402.2817
A8: Value
A9: PV of FY2027-FY2031 free cash flow | B9: $m | C9: =SUM(Model!$C$22:$G$22) -> 1237.1937
A10: DCF value of Jordan | B10: $m | C10: =$C$9+$C$7 -> 5639.4754
A11: Value per NKE share | B11: $ | C11: =$C$10/Inputs!$C$12 -> 3.7925188
A12: Share of NKE price | B12: % | C12: =$C$11/Inputs!$C$11 -> 0.10728483
A13: Terminal value share of DCF value | B13: % | C13: =$C$7/$C$10 -> 0.78061901
A14: FY2031 snapshot
A15: EBIT FY2031 | B15: $m | C15: =Model!$G$17 -> 738.50528
A16: EPS contribution FY2031 | B16: $ | C16: =$C$15*(1-Inputs!$C$14)/Inputs!$C$12 -> 0.38489684
A17: FY2031 revenue vs FY2024 peak | B17: % | C17: =Model!$G$14/Inputs!$C$9-1 -> -0.22840083

Sheet Charts
A1: Charts
A3: Jordan DCF value, active scenario ($m)
A4: Step | B4: Value | C4: Running total | D4: Base | E4: Increase | F4: Decrease | G4: Total
A5: PV FY2027 FCF | B5: =Model!$C$22 -> 161.47292 | C5: =B5 -> 161.47292 | G5: =B5 -> 161.47292
A6: PV FY2028 FCF | B6: =Model!$D$22 -> 283.50931 | C6: =C5+B6 -> 444.98223 | D6: =MIN(C5,C6) -> 161.47292 | E6: =MAX(B6,0) -> 283.50931 | F6: =MAX(-B6,0) -> 0
A7: PV FY2029 FCF | B7: =Model!$E$22 -> 226.98556 | C7: =C6+B7 -> 671.96779 | D7: =MIN(C6,C7) -> 444.98223 | E7: =MAX(B7,0) -> 226.98556 | F7: =MAX(-B7,0) -> 0
A8: PV FY2030 FCF | B8: =Model!$F$22 -> 265.3906 | C8: =C7+B8 -> 937.35839 | D8: =MIN(C7,C8) -> 671.96779 | E8: =MAX(B8,0) -> 265.3906 | F8: =MAX(-B8,0) -> 0
A9: PV FY2031 FCF | B9: =Model!$G$22 -> 299.83529 | C9: =C8+B9 -> 1237.1937 | D9: =MIN(C8,C9) -> 937.35839 | E9: =MAX(B9,0) -> 299.83529 | F9: =MAX(-B9,0) -> 0
A10: PV terminal value | B10: =Valuation!$C$7 -> 4402.2817 | C10: =C9+B10 -> 5639.4754 | D10: =MIN(C9,C10) -> 1237.1937 | E10: =MAX(B10,0) -> 4402.2817 | F10: =MAX(-B10,0) -> 0
A11: End | C11: =C10 -> 5639.4754 | G11: =C11 -> 5639.4754
A12: Live: follows the scenario switch on Inputs. End bar equals Valuation 'DCF value of Jordan'.
A36: Jordan value per NKE share ($)
A37: Method | B37: Low | C37: High | D37: Range | E37: Source
A38: DCF, Bear to Bull scenarios | B38: 2.32 | C38: 5.96 | D38: =C38-B38 -> 3.64 | E38: data/valuation/jordan_scenarios.csv (scripts/jordan_valuation.py)
A39: DCF, Base path, margin 6% to 17% | B39: 2.14 | C39: 5.78 | D39: =C39-B39 -> 3.64 | E39: data/valuation/jordan_sensitivity.csv
A40: DCF, Bear path, margin 6% to 17% | B40: 1.82 | C40: 4.57 | D40: =C40-B40 -> 2.75 | E40: data/valuation/jordan_sensitivity.csv
A41: Jordan FY2026 revenue x NKE EV/Sales | B41: 5.68 | C41: 5.7 | D41: =C41-B41 -> 0.02 | E41: jordan_scenarios.csv reference row (point estimate)
A42: Live scenario value per share | B42: =F42-ABS(F42)*G42 -> 3.7735562 | C42: =F42+ABS(F42)*G42 -> 3.8114814 | D42: =C42-B42 -> 0.037925188 | E42: live marker (column F), drawn as a sliver of width set in column G | F42: =Valuation!$C$11 -> 3.7925188 | G42: 0.005
A44: Static ranges are outputs of scripts/jordan_valuation.py; the marker is live.

Sheet Checks
A1: Check | B1: Value | C1: Tolerance | D1: Pass (1/0)
A2: Margin reaches target in FY2031 | B2: =Model!$G$16-Inputs!$C$21 -> 0 | C2: 0.001 | D2: =IF(ABS(B2)<=C2,1,0) -> 1
A3: Terminal growth below WACC | B3: =IF(Inputs!$C$22<Inputs!$C$17,1,0) -> 1 | C3: must be 1 | D3: =B3 -> 1
A4: Revenue never negative | B4: =IF(MIN(Model!$C$14:$G$14)>=0,1,0) -> 1 | C4: must be 1 | D4: =B4 -> 1
A5: Value = PV(FCF) + PV(TV) | B5: =Valuation!$C$10-SUM(Model!$C$22:$G$22)-Valuation!$C$7 -> 0 | C5: 0.001 | D5: =IF(ABS(B5)<=C5,1,0) -> 1
A6: Discount timing: final period ends at stub + (periods - 1) years | B6: =Model!$G$7-(Inputs!$C$19+MAX(Model!$C$5:$G$5)-1) -> 0 | C6: 0.001 | D6: =IF(ABS(B6)<=C6,1,0) -> 1
A7: Jordan DCF value, active scenario ($m): bars reconcile | B7: =Charts!$G$11-Charts!$B$5-SUM(Charts!$B$6:$B$10) -> 0 | C7: 0.001 | D7: =IF(ABS(B7)<=C7,1,0) -> 1
A9: Master check (1 = all pass) | D9: =IF(SUM(D2:D7)=COUNT(D2:D7),1,0) -> 1
